WiPi/__init__.py
WiPi/access_point.py
WiPi/constants.py
WiPi/interface.py
WiPi/wifi.py
WiPi/bin/linux/iw_interface
WiPi/bin/linux/access_point/status
WiPi/bin/linux/wifi/iw_link
WiPi/bin/linux/wifi/iw_scan
WiPi/bin/linux/wifi/network
WiPi/bin/linux/wifi/reset
WiPi/bin/linux/wifi/set
WiPi/bin/linux/wifi/status
WiPi/bin/linux/wifi/wpa_passphrase
WiPi/bin/linux/wifi/wpa_supplicant
WiPi/bin/win32/scan
WiPi/linux/__init__.py
WiPi/linux/access_point.py
WiPi/linux/wifi.py
WiPi/win32/__init__.py
WiPi/win32/wifi.py
WiPi-0.0.10.dist-info/LICENSE
WiPi-0.0.10.dist-info/METADATA
WiPi-0.0.10.dist-info/WHEEL
WiPi-0.0.10.dist-info/top_level.txt
WiPi-0.0.10.dist-info/RECORD
