Metadata-Version: 2.1
Name: WiPi
Version: 0.0.10
Summary: A general use class based WPA network manager
Home-page: https://github.com/ryanchaiyakul/WiPi
Author: Ryan Chaiyakul
License: UNKNOWN
Platform: UNKNOWN
Classifier: Programming Language :: Python :: 3
Classifier: License :: OSI Approved :: MIT License
Classifier: Operating System :: OS Independent
Requires-Python: >=3.6
Requires-Dist: netifaces (>=0.10.9)
Requires-Dist: psutil (>=5.6.7)
Requires-Dist: PyAccessPoint (>=0.2.5)
Requires-Dist: wireless (>=0.3.3)
